apify_fingerprint_datapoints/CHANGELOG.md
apify_fingerprint_datapoints/README.md
apify_fingerprint_datapoints/__init__.py
apify_fingerprint_datapoints/py.typed
apify_fingerprint_datapoints/data/browser-helper-file.json
apify_fingerprint_datapoints/data/fingerprint-network-definition.zip
apify_fingerprint_datapoints/data/header-network-definition.zip
apify_fingerprint_datapoints/data/headers-order.json
apify_fingerprint_datapoints/data/input-network-definition.zip
apify_fingerprint_datapoints-0.6.0.dist-info/METADATA
apify_fingerprint_datapoints-0.6.0.dist-info/WHEEL
apify_fingerprint_datapoints-0.6.0.dist-info/licenses/LICENSE.md
apify_fingerprint_datapoints-0.6.0.dist-info/RECORD
