Metadata-Version: 2.4
Name: apify_fingerprint_datapoints
Version: 0.6.0
Summary: Browser fingerprint datapoints collected by Apify
Project-URL: Homepage, https://docs.apify.com/academy/anti-scraping/techniques/fingerprinting
Project-URL: Apify homepage, https://apify.com
Project-URL: Changelog, https://github.com/apify/fingerprint-suite/blob/master/apify_fingerprint_datapoints/CHANGELOG.md
Project-URL: Documentation, https://docs.apify.com/academy/anti-scraping/techniques/fingerprinting
Project-URL: Issue tracker, https://github.com/apify/fingerprint-suite/issues
Project-URL: Repository, https://github.com/apify/fingerprint-suite
Author-email: "Apify Technologies s.r.o." <support@apify.com>
License:                                  Apache License
License-File: LICENSE.md
Keywords: apify,chrome,crawlee,crawler,fingerprints,scraper,scraping
Classifier: Development Status :: 5 - Production/Stable
Classifier: Intended Audience :: Developers
Classifier: License :: OSI Approved :: Apache Software License
Classifier: Operating System :: OS Independent
Classifier: Programming Language :: Python :: 3.8
Classifier: Programming Language :: Python :: 3.9
Classifier: Programming Language :: Python :: 3.10
Classifier: Programming Language :: Python :: 3.11
Classifier: Programming Language :: Python :: 3.12
Classifier: Programming Language :: Python :: 3.13
Classifier: Topic :: Software Development :: Libraries
Requires-Python: >=3.8
